library-3.0.160.dist-info/METADATA
library-3.0.160.dist-info/WHEEL
library-3.0.160.dist-info/entry_points.txt
library-3.0.160.dist-info/licenses/LICENSE
library/__init__.py
library/__main__.py
library/assets/__init__.py
library/assets/calibre.css
library/assets/kotobago.png
library/createdb/__init__.py
library/createdb/av.py
library/createdb/computer_info.py
library/createdb/computers_add.py
library/createdb/fs_add.py
library/createdb/fs_add_metadata.py
library/createdb/gallery_add.py
library/createdb/gallery_backend.py
library/createdb/getty_add.py
library/createdb/hn_add.py
library/createdb/links_add.py
library/createdb/nicotine_import.py
library/createdb/places_import.py
library/createdb/reddit_add.py
library/createdb/row_add.py
library/createdb/site_add.py
library/createdb/substack.py
library/createdb/subtitle.py
library/createdb/tables_add.py
library/createdb/tabs_add.py
library/createdb/tildes.py
library/createdb/torrents_add.py
library/createdb/tube_add.py
library/createdb/tube_backend.py
library/createdb/web_add.py
library/data/__init__.py
library/data/dictionary.pkl
library/data/ffmpeg_errors.py
library/data/http_errors.py
library/data/imagemagick_errors.py
library/data/unar_errors.py
library/data/wordbank.py
library/data/yt_dlp_errors.py
library/editdb/__init__.py
library/editdb/dedupe_db.py
library/editdb/dedupe_media.py
library/editdb/merge_online_local.py
library/editdb/mpv_watchlater.py
library/editdb/pushshift.py
library/editdb/reddit_selftext.py
library/files/__init__.py
library/files/christen.py
library/files/llm_map.py
library/files/sample_compare.py
library/files/sample_hash.py
library/files/similar_files.py
library/folders/__init__.py
library/folders/big_dirs.py
library/folders/filter_src.py
library/folders/merge_folders.py
library/folders/merge_mv.py
library/folders/mergerfs_cp.py
library/folders/mount_stats.py
library/folders/move_list.py
library/folders/scatter.py
library/folders/similar_folders.py
library/fsdb/__init__.py
library/fsdb/disk_usage.py
library/fsdb/files_info.py
library/fsdb/search_db.py
library/lb.py
library/mediadb/__init__.py
library/mediadb/block.py
library-3.0.160.dist-info/RECORD
