Metadata-Version: 2.1
Name: library
Version: 3.0.160
Summary: xk media library
Author-Email: Jacob Chapman <7908073+chapmanjacobd@users.noreply.github.com>
License: BSD 3-Clause License
Project-URL: documentation, https://github.com/chapmanjacobd/library#usage
Project-URL: homepage, https://github.com/chapmanjacobd/library#readme
Project-URL: repository, https://github.com/chapmanjacobd/library/
Requires-Python: >=3.11
Requires-Dist: beautifulsoup4>=4.10.0
Requires-Dist: sqlite-utils>=3.38
Requires-Dist: ipython>=9.0.0
Requires-Dist: ffmpeg-python
Requires-Dist: gallery-dl
Requires-Dist: yt-dlp[curl-cffi,default]
Requires-Dist: natsort
Requires-Dist: charset-normalizer
Requires-Dist: puremagic
Requires-Dist: ftfy
Requires-Dist: wcwidth
Requires-Dist: humanize
Requires-Dist: lxml
Requires-Dist: markdown-it-py
Requires-Dist: mutagen
Requires-Dist: praw
Requires-Dist: pysubs2
Requires-Dist: python-dateutil
Requires-Dist: python-mpv-jsonipc
Requires-Dist: regex
Requires-Dist: rich
Requires-Dist: screeninfo
Requires-Dist: tabulate
Requires-Dist: tinytag
Requires-Dist: tldextract
Requires-Dist: pyreadline3; platform_system == "Windows"
Provides-Extra: dev
Requires-Dist: black; extra == "dev"
Requires-Dist: isort; extra == "dev"
Requires-Dist: ssort; extra == "dev"
Provides-Extra: test
Requires-Dist: ruff; extra == "test"
Requires-Dist: pytest; extra == "test"
Requires-Dist: pytest-regressions; extra == "test"
Requires-Dist: freezegun; extra == "test"
Requires-Dist: pandas; extra == "test"
Requires-Dist: pyfakefs; extra == "test"
Provides-Extra: deluxe
Requires-Dist: aiohttp; extra == "deluxe"
Requires-Dist: annoy; extra == "deluxe"
Requires-Dist: catt; extra == "deluxe"
Requires-Dist: geopandas; extra == "deluxe"
Requires-Dist: img2pdf; extra == "deluxe"
Requires-Dist: ocrmypdf; extra == "deluxe"
Requires-Dist: openpyxl; extra == "deluxe"
Requires-Dist: paramiko; extra == "deluxe"
Requires-Dist: pdf2image; extra == "deluxe"
Requires-Dist: pillow; extra == "deluxe"
Requires-Dist: PyExifTool; extra == "deluxe"
Requires-Dist: pymcdm; extra == "deluxe"
Requires-Dist: pyvirtualdisplay; extra == "deluxe"
Requires-Dist: qbittorrent-api; extra == "deluxe"
Requires-Dist: scikit-learn; extra == "deluxe"
Requires-Dist: selenium; extra == "deluxe"
Requires-Dist: libtorrent; extra == "deluxe"
Requires-Dist: tqdm; extra == "deluxe"
Requires-Dist: wordllama>=0.2.7.post0; extra == "deluxe"
Requires-Dist: xattr; extra == "deluxe"
Provides-Extra: fat
Requires-Dist: brotab; extra == "fat"
Requires-Dist: camelot-py>=0.11.0; extra == "fat"
Requires-Dist: ghostscript; extra == "fat"
Requires-Dist: opencv-python; extra == "fat"
Requires-Dist: orjson; extra == "fat"
Requires-Dist: selenium-wire; extra == "fat"
Requires-Dist: subliminal; extra == "fat"
Requires-Dist: textract-py3==2.0.1; extra == "fat"
